{
  "$schema": "https://developer.microsoft.com/json-schemas/spfx-build/spfx-serve.schema.json",
  "port": 4321,
  "https": true,
  "serveConfigurations": {
    "default": {
      "pageUrl": "https://{tenantDomain}/SitePages/myPage.aspx",
      "customActions": {
        "66607c85-0142-4caf-ba34-d4185a4999f1": {
          "location": "ClientSideExtension.ApplicationCustomizer",
          "properties": {
            "testMessage": "Test message"
          }
        }
      }
    },
    "polcss": {
      "pageUrl": "https://{tenantDomain}/SitePages/myPage.aspx",
      "customActions": {
        "66607c85-0142-4caf-ba34-d4185a4999f1": {
          "location": "ClientSideExtension.ApplicationCustomizer",
          "properties": {
            "testMessage": "Test message"
          }
        }
      }
    }
  }
}
